config.py
promptcache/__init__.py
promptcache/embedding.py
promptcache/redis.py
promptcache/timeddict.py
promptcache-0.0.1a1.dist-info/LICENSE
promptcache-0.0.1a1.dist-info/METADATA
promptcache-0.0.1a1.dist-info/WHEEL
promptcache-0.0.1a1.dist-info/RECORD
